Metadata-Version: 2.1
Name: odoo-addon-maintenance_timesheet
Version: 18.0.1.1.0.4
Requires-Python: >=3.10
Requires-Dist: odoo-addon-maintenance_project==18.0.*
Requires-Dist: odoo==18.0.*
Summary: Adds timesheets to maintenance requests
Home-page: https://github.com/OCA/maintenance
License: AGPL-3
Author: Odoo Community Association (OCA), Solvos
Author-email: support@odoo-community.org
Classifier: Programming Language :: Python
Classifier: Framework :: Odoo
Classifier: Framework :: Odoo :: 18.0
Classifier: License :: OSI Approved :: GNU Affero General Public License v3
